imgstore/__init__.py
imgstore/align.py
imgstore/apps.py
imgstore/constants.py
imgstore/font.py
imgstore/index.py
imgstore/stores.py
imgstore/ui.py
imgstore/util.py
imgstore/tests/__init__.py
imgstore/tests/test_imgstore.py
imgstore/tests/test_util.py
imgstore/tests/data/graffiti.png
imgstore/tests/data/store_mp4/000000.mp4
imgstore/tests/data/store_mp4/000000.npz
imgstore/tests/data/store_mp4/000001.mp4
imgstore/tests/data/store_mp4/000001.npz
imgstore/tests/data/store_mp4/metadata.yaml
imgstore-0.3.7.dist-info/LICENSE.txt
imgstore-0.3.7.dist-info/METADATA
imgstore-0.3.7.dist-info/WHEEL
imgstore-0.3.7.dist-info/entry_points.txt
imgstore-0.3.7.dist-info/top_level.txt
imgstore-0.3.7.dist-info/RECORD
