Metadata-Version: 2.1
Name: imgstore
Version: 0.3.7
Summary: IMGStore houses your video frames
Home-page: https://github.com/loopbio/imgstore
Author: John Stowers, Santi Villalba
Author-email: john@loopbio.com, santi@loopbio.com
License: BSD 3 clause
Classifier: Intended Audience :: Science/Research
Classifier: Intended Audience :: Developers
Classifier: Topic :: Software Development
Classifier: Topic :: Scientific/Engineering
Classifier: License :: OSI Approved
Classifier: Programming Language :: Python :: 3.6
Classifier: Programming Language :: Python :: 3.7
Classifier: Programming Language :: Python :: 3.8
Classifier: Programming Language :: Python :: 3.9
Classifier: Programming Language :: Python :: 3.10
Requires-Python: >=3.6
License-File: LICENSE.txt
Requires-Dist: numpy
Requires-Dist: pandas
Requires-Dist: pyyaml
Requires-Dist: tzlocal
Requires-Dist: python-dateutil
Requires-Dist: backports.zoneinfo ; python_version < "3.9.0"
Provides-Extra: bloscpack
Requires-Dist: bloscpack ; extra == 'bloscpack'
